[
    {
        "question": "What is the capital of USA?",
        "answers": [
          { "text": "St Paul", "isCorrect": false },
          { "text": "Patriotville", "isCorrect": false },
          { "text": "New York City", "isCorrect": false },
          { "text": "Washington DC", "isCorrect": true }
        ]
      },
      {
        "question": "What is 2 + 2?",
        "answers": [
          { "text": "6", "isCorrect": false },
          { "text": "4", "isCorrect": true },
          { "text": "9", "isCorrect": false },
          { "text": "7", "isCorrect": false }
        ]
      },
      {
        "question": "What is 10 + 2?",
        "answers": [
          { "text": "6", "isCorrect": false },
          { "text": "12", "isCorrect": true },
          { "text": "9", "isCorrect": false },
          { "text": "7", "isCorrect": false }
        ]
      }

  ]
    